[{"geoid": "300310001011", "enrollmentScore": 4.65568316666667, "enrollmentScorePlus": 189.0256960938672, "wealthScore": 415.68, "colors": {"absolute": null, "absolutePlus": null, "esAbsolute": "#3b82f6", "esPlusAbsolute": "#3b82f6", "wsAbsolute": "#3b82f6", "esRelative": "#eab308", "esPlusRelative": "#eab308", "wsRelative": "#eab308", "comboRelative": "#eab308", "comboPlusRelative": "#eab308", "es": "#eab308", "esPlus": "#eab308", "ws": "#eab308", "combo": "#eab308", "comboPlus": "#eab308", "esFiltered": null, "wsFiltered": null, "comboFiltered": null, "esPlusFiltered": null, "wsPlusFiltered": null, "comboPlusFiltered": null, "esRelativeFiltered": null, "wsRelativeFiltered": null, "comboRelativeFiltered": null, "esPlusRelativeFiltered": null, "comboPlusRelativeFiltered": null}}, {"geoid": "300310001012", "enrollmentScore": 8.6926203619313, "enrollmentScorePlus": 272.09647502653036, "wealthScore": 554.14, "colors": {"absolute": null, "absolutePlus": null, "esAbsolute": "#3b82f6", "esPlusAbsolute": "#3b82f6", "wsAbsolute": "#3b82f6", "esRelative": "#f97316", "esPlusRelative": "#f97316", "wsRelative": "#f97316", "comboRelative": "#f97316", "comboPlusRelative": "#f97316", "es": "#eab308", "esPlus": "#eab308", "ws": "#eab308", "combo": "#eab308", "comboPlus": "#eab308", "esFiltered": null, "wsFiltered": null, "comboFiltered": null, "esPlusFiltered": null, "wsPlusFiltered": null, "comboPlusFiltered": null, "esRelativeFiltered": null, "wsRelativeFiltered": null, "comboRelativeFiltered": null, "esPlusRelativeFiltered": null, "comboPlusRelativeFiltered": null}}, {"geoid": "300310001013", "enrollmentScore": 1.39179223333333, "enrollmentScorePlus": 126.19212917062353, "wealthScore": 335.12, "colors": {"absolute": null, "absolutePlus": null, "esAbsolute": "#3b82f6", "esPlusAbsolute": "#3b82f6", "wsAbsolute": "#3b82f6", "esRelative": "#3b82f6", "esPlusRelative": "#eab308", "wsRelative": "#eab308", "comboRelative": "#3b82f6", "comboPlusRelative": "#eab308", "es": "#3b82f6", "esPlus": "#3b82f6", "ws": "#3b82f6", "combo": "#3b82f6", "comboPlus": "#3b82f6", "esFiltered": null, "wsFiltered": null, "comboFiltered": null, "esPlusFiltered": null, "wsPlusFiltered": null, "comboPlusFiltered": null, "esRelativeFiltered": null, "wsRelativeFiltered": null, "comboRelativeFiltered": null, "esPlusRelativeFiltered": null, "comboPlusRelativeFiltered": null}}, {"geoid": "300310001014", "enrollmentScore": 0.726404566666667, "enrollmentScorePlus": 88.74616081702423, "wealthScore": 170.31, "colors": {"absolute": null, "absolutePlus": null, "esAbsolute": "#3b82f6", "esPlusAbsolute": "#3b82f6", "wsAbsolute": "#3b82f6", "esRelative": "#3b82f6", "esPlusRelative": "#3b82f6", "wsRelative": "#3b82f6", "comboRelative": "#3b82f6", "comboPlusRelative": "#3b82f6", "es": "#3b82f6", "esPlus": "#3b82f6", "ws": "#3b82f6", "combo": "#3b82f6", "comboPlus": "#3b82f6", "esFiltered": null, "wsFiltered": null, "comboFiltered": null, "esPlusFiltered": null, "wsPlusFiltered": null, "comboPlusFiltered": null, "esRelativeFiltered": null, "wsRelativeFiltered": null, "comboRelativeFiltered": null, "esPlusRelativeFiltered": null, "comboPlusRelativeFiltered": null}}, {"geoid": "300310001041", "enrollmentScore": 2.70155176666667, "enrollmentScorePlus": 187.64664560787634, "wealthScore": 378.72, "colors": {"absolute": null, "absolutePlus": null, "esAbsolute": "#3b82f6", "esPlusAbsolute": "#3b82f6", "wsAbsolute": "#3b82f6", "esRelative": "#3b82f6", "esPlusRelative": "#eab308", "wsRelative": "#eab308", "comboRelative": "#3b82f6", "comboPlusRelative": "#eab308", "es": "#3b82f6", "esPlus": "#eab308", "ws": "#eab308", "combo": "#3b82f6", "comboPlus": "#eab308", "esFiltered": null, "wsFiltered": null, "comboFiltered": null, "esPlusFiltered": null, "wsPlusFiltered": null, "comboPlusFiltered": null, "esRelativeFiltered": null, "wsRelativeFiltered": null, "comboRelativeFiltered": null, "esPlusRelativeFiltered": null, "comboPlusRelativeFiltered": null}}, {"geoid": "300310001042", "enrollmentScore": 1.41455935, "enrollmentScorePlus": 145.86830185841606, "wealthScore": 335.84, "colors": {"absolute": null, "absolutePlus": null, "esAbsolute": "#3b82f6", "esPlusAbsolute": "#3b82f6", "wsAbsolute": "#3b82f6", "esRelative": "#3b82f6", "esPlusRelative": "#eab308", "wsRelative": "#eab308", "comboRelative": "#3b82f6", "comboPlusRelative": "#eab308", "es": "#3b82f6", "esPlus": "#eab308", "ws": "#3b82f6", "combo": "#3b82f6", "comboPlus": "#3b82f6", "esFiltered": null, "wsFiltered": null, "comboFiltered": null, "esPlusFiltered": null, "wsPlusFiltered": null, "comboPlusFiltered": null, "esRelativeFiltered": null, "wsRelativeFiltered": null, "comboRelativeFiltered": null, "esPlusRelativeFiltered": null, "comboPlusRelativeFiltered": null}}, {"geoid": "300310001051", "enrollmentScore": 4.66506437277598, "enrollmentScorePlus": 242.77283695151385, "wealthScore": 582.85, "colors": {"absolute": null, "absolutePlus": null, "esAbsolute": "#3b82f6", "esPlusAbsolute": "#3b82f6", "wsAbsolute": "#3b82f6", "esRelative": "#eab308", "esPlusRelative": "#f97316", "wsRelative": "#f97316", "comboRelative": "#eab308", "comboPlusRelative": "#f97316", "es": "#eab308", "esPlus": "#eab308", "ws": "#eab308", "combo": "#eab308", "comboPlus": "#eab308", "esFiltered": null, "wsFiltered": null, "comboFiltered": null, "esPlusFiltered": null, "wsPlusFiltered": null, "comboPlusFiltered": null, "esRelativeFiltered": null, "wsRelativeFiltered": null, "comboRelativeFiltered": null, "esPlusRelativeFiltered": null, "comboPlusRelativeFiltered": null}}, {"geoid": "300310001052", "enrollmentScore": 3.59807098333333, "enrollmentScorePlus": 218.75907442455917, "wealthScore": 486.84, "colors": {"absolute": null, "absolutePlus": null, "esAbsolute": "#3b82f6", "esPlusAbsolute": "#3b82f6", "wsAbsolute": "#3b82f6", "esRelative": "#eab308", "esPlusRelative": "#eab308", "wsRelative": "#f97316", "comboRelative": "#eab308", "comboPlusRelative": "#eab308", "es": "#3b82f6", "esPlus": "#eab308", "ws": "#eab308", "combo": "#3b82f6", "comboPlus": "#eab308", "esFiltered": null, "wsFiltered": null, "comboFiltered": null, "esPlusFiltered": null, "wsPlusFiltered": null, "comboPlusFiltered": null, "esRelativeFiltered": null, "wsRelativeFiltered": null, "comboRelativeFiltered": null, "esPlusRelativeFiltered": null, "comboPlusRelativeFiltered": null}}, {"geoid": "300310001053", "enrollmentScore": 5.8559943619313, "enrollmentScorePlus": 270.00505082721804, "wealthScore": 582.85, "colors": {"absolute": null, "absolutePlus": null, "esAbsolute": "#3b82f6", "esPlusAbsolute": "#3b82f6", "wsAbsolute": "#3b82f6", "esRelative": "#eab308", "esPlusRelative": "#f97316", "wsRelative": "#f97316", "comboRelative": "#eab308", "comboPlusRelative": "#f97316", "es": "#eab308", "esPlus": "#eab308", "ws": "#eab308", "combo": "#eab308", "comboPlus": "#eab308", "esFiltered": null, "wsFiltered": null, "comboFiltered": null, "esPlusFiltered": null, "wsPlusFiltered": null, "comboPlusFiltered": null, "esRelativeFiltered": null, "wsRelativeFiltered": null, "comboRelativeFiltered": null, "esPlusRelativeFiltered": null, "comboPlusRelativeFiltered": null}}, {"geoid": "300310002011", "enrollmentScore": 3.59807098333333, "enrollmentScorePlus": 197.90830307100316, "wealthScore": 450.28, "colors": {"absolute": null, "absolutePlus": null, "esAbsolute": "#3b82f6", "esPlusAbsolute": "#3b82f6", "wsAbsolute": "#3b82f6", "esRelative": "#eab308", "esPlusRelative": "#eab308", "wsRelative": "#f97316", "comboRelative": "#eab308", "comboPlusRelative": "#eab308", "es": "#3b82f6", "esPlus": "#eab308", "ws": "#eab308", "combo": "#3b82f6", "comboPlus": "#eab308", "esFiltered": null, "wsFiltered": null, "comboFiltered": null, "esPlusFiltered": null, "wsPlusFiltered": null, "comboPlusFiltered": null, "esRelativeFiltered": null, "wsRelativeFiltered": null, "comboRelativeFiltered": null, "esPlusRelativeFiltered": null, "comboPlusRelativeFiltered": null}}, {"geoid": "300310002012", "enrollmentScore": 0.742166416666667, "enrollmentScorePlus": 96.18429961099129, "wealthScore": 116.78, "colors": {"absolute": null, "absolutePlus": null, "esAbsolute": "#3b82f6", "esPlusAbsolute": "#3b82f6", "wsAbsolute": "#3b82f6", "esRelative": "#3b82f6", "esPlusRelative": "#3b82f6", "wsRelative": "#3b82f6", "comboRelative": "#3b82f6", "comboPlusRelative": "#3b82f6", "es": "#3b82f6", "esPlus": "#3b82f6", "ws": "#3b82f6", "combo": "#3b82f6", "comboPlus": "#3b82f6", "esFiltered": null, "wsFiltered": null, "comboFiltered": null, "esPlusFiltered": null, "wsPlusFiltered": null, "comboPlusFiltered": null, "esRelativeFiltered": null, "wsRelativeFiltered": null, "comboRelativeFiltered": null, "esPlusRelativeFiltered": null, "comboPlusRelativeFiltered": null}}, {"geoid": "300310002013", "enrollmentScore": 3.59807098333333, "enrollmentScorePlus": 209.25920632629635, "wealthScore": 450.28, "colors": {"absolute": null, "absolutePlus": null, "esAbsolute": "#3b82f6", "esPlusAbsolute": "#3b82f6", "wsAbsolute": "#3b82f6", "esRelative": "#eab308", "esPlusRelative": "#eab308", "wsRelative": "#f97316", "comboRelative": "#eab308", "comboPlusRelative": "#eab308", "es": "#3b82f6", "esPlus": "#eab308", "ws": "#eab308", "combo": "#3b82f6", "comboPlus": "#eab308", "esFiltered": null, "wsFiltered": null, "comboFiltered": null, "esPlusFiltered": null, "wsPlusFiltered": null, "comboPlusFiltered": null, "esRelativeFiltered": null, "wsRelativeFiltered": null, "comboRelativeFiltered": null, "esPlusRelativeFiltered": null, "comboPlusRelativeFiltered": null}}, {"geoid": "300310002021", "enrollmentScore": 5.83761066666667, "enrollmentScorePlus": 254.71170982659766, "wealthScore": 635.83, "colors": {"absolute": null, "absolutePlus": null, "esAbsolute": "#3b82f6", "esPlusAbsolute": "#3b82f6", "wsAbsolute": "#3b82f6", "esRelative": "#eab308", "esPlusRelative": "#f97316", "wsRelative": "#f97316", "comboRelative": "#eab308", "comboPlusRelative": "#f97316", "es": "#eab308", "esPlus": "#eab308", "ws": "#eab308", "combo": "#eab308", "comboPlus": "#eab308", "esFiltered": null, "wsFiltered": null, "comboFiltered": null, "esPlusFiltered": null, "wsPlusFiltered": null, "comboPlusFiltered": null, "esRelativeFiltered": null, "wsRelativeFiltered": null, "comboRelativeFiltered": null, "esPlusRelativeFiltered": null, "comboPlusRelativeFiltered": null}}, {"geoid": "300310003001", "enrollmentScore": 0.249024176775782, "enrollmentScorePlus": 35.513172324178456, "wealthScore": 23.24, "colors": {"absolute": null, "absolutePlus": null, "esAbsolute": "#3b82f6", "esPlusAbsolute": "#3b82f6", "wsAbsolute": "#3b82f6", "esRelative": "#3b82f6", "esPlusRelative": "#3b82f6", "wsRelative": "#3b82f6", "comboRelative": "#3b82f6", "comboPlusRelative": "#3b82f6", "es": "#3b82f6", "esPlus": "#3b82f6", "ws": "#3b82f6", "combo": "#3b82f6", "comboPlus": "#3b82f6", "esFiltered": null, "wsFiltered": null, "comboFiltered": null, "esPlusFiltered": null, "wsPlusFiltered": null, "comboPlusFiltered": null, "esRelativeFiltered": null, "wsRelativeFiltered": null, "comboRelativeFiltered": null, "esPlusRelativeFiltered": null, "comboPlusRelativeFiltered": null}}, {"geoid": "300310003002", "enrollmentScore": 0.0628075068724368, "enrollmentScorePlus": 16.6150555053097, "wealthScore": 21.5, "colors": {"absolute": null, "absolutePlus": null, "esAbsolute": "#3b82f6", "esPlusAbsolute": "#3b82f6", "wsAbsolute": "#3b82f6", "esRelative": "#3b82f6", "esPlusRelative": "#3b82f6", "wsRelative": "#3b82f6", "comboRelative": "#3b82f6", "comboPlusRelative": "#3b82f6", "es": "#3b82f6", "esPlus": "#3b82f6", "ws": "#3b82f6", "combo": "#3b82f6", "comboPlus": "#3b82f6", "esFiltered": null, "wsFiltered": null, "comboFiltered": null, "esPlusFiltered": null, "wsPlusFiltered": null, "comboPlusFiltered": null, "esRelativeFiltered": null, "wsRelativeFiltered": null, "comboRelativeFiltered": null, "esPlusRelativeFiltered": null, "comboPlusRelativeFiltered": null}}, {"geoid": "300310003003", "enrollmentScore": 0.00133655861490197, "enrollmentScorePlus": 10.733961460211868, "wealthScore": 4.97, "colors": {"absolute": null, "absolutePlus": null, "esAbsolute": "#3b82f6", "esPlusAbsolute": "#3b82f6", "wsAbsolute": "#3b82f6", "esRelative": "#3b82f6", "esPlusRelative": "#3b82f6", "wsRelative": "#3b82f6", "comboRelative": "#3b82f6", "comboPlusRelative": "#3b82f6", "es": "#3b82f6", "esPlus": "#3b82f6", "ws": "#3b82f6", "combo": "#3b82f6", "comboPlus": "#3b82f6", "esFiltered": null, "wsFiltered": null, "comboFiltered": null, "esPlusFiltered": null, "wsPlusFiltered": null, "comboPlusFiltered": null, "esRelativeFiltered": null, "wsRelativeFiltered": null, "comboRelativeFiltered": null, "esPlusRelativeFiltered": null, "comboPlusRelativeFiltered": null}}, {"geoid": "300310004001", "enrollmentScore": 0.197650620089695, "enrollmentScorePlus": 36.02372864669351, "wealthScore": 45.44, "colors": {"absolute": null, "absolutePlus": null, "esAbsolute": "#3b82f6", "esPlusAbsolute": "#3b82f6", "wsAbsolute": "#3b82f6", "esRelative": "#3b82f6", "esPlusRelative": "#3b82f6", "wsRelative": "#3b82f6", "comboRelative": "#3b82f6", "comboPlusRelative": "#3b82f6", "es": "#3b82f6", "esPlus": "#3b82f6", "ws": "#3b82f6", "combo": "#3b82f6", "comboPlus": "#3b82f6", "esFiltered": null, "wsFiltered": null, "comboFiltered": null, "esPlusFiltered": null, "wsPlusFiltered": null, "comboPlusFiltered": null, "esRelativeFiltered": null, "wsRelativeFiltered": null, "comboRelativeFiltered": null, "esPlusRelativeFiltered": null, "comboPlusRelativeFiltered": null}}, {"geoid": "300310004002", "enrollmentScore": 0, "enrollmentScorePlus": 14.747934572058394, "wealthScore": 1.45, "colors": {"absolute": null, "absolutePlus": null, "esAbsolute": null, "esPlusAbsolute": "#3b82f6", "wsAbsolute": "#3b82f6", "esRelative": null, "esPlusRelative": "#3b82f6", "wsRelative": "#3b82f6", "comboRelative": null, "comboPlusRelative": "#3b82f6", "es": null, "esPlus": "#3b82f6", "ws": "#3b82f6", "combo": null, "comboPlus": "#3b82f6", "esFiltered": null, "wsFiltered": null, "comboFiltered": null, "esPlusFiltered": null, "wsPlusFiltered": null, "comboPlusFiltered": null, "esRelativeFiltered": null, "wsRelativeFiltered": null, "comboRelativeFiltered": null, "esPlusRelativeFiltered": null, "comboPlusRelativeFiltered": null}}, {"geoid": "300310004003", "enrollmentScore": 0.742166416666667, "enrollmentScorePlus": 96.66286874724778, "wealthScore": 170.59, "colors": {"absolute": null, "absolutePlus": null, "esAbsolute": "#3b82f6", "esPlusAbsolute": "#3b82f6", "wsAbsolute": "#3b82f6", "esRelative": "#3b82f6", "esPlusRelative": "#3b82f6", "wsRelative": "#3b82f6", "comboRelative": "#3b82f6", "comboPlusRelative": "#3b82f6", "es": "#3b82f6", "esPlus": "#3b82f6", "ws": "#3b82f6", "combo": "#3b82f6", "comboPlus": "#3b82f6", "esFiltered": null, "wsFiltered": null, "comboFiltered": null, "esPlusFiltered": null, "wsPlusFiltered": null, "comboPlusFiltered": null, "esRelativeFiltered": null, "wsRelativeFiltered": null, "comboRelativeFiltered": null, "esPlusRelativeFiltered": null, "comboPlusRelativeFiltered": null}}, {"geoid": "300310004004", "enrollmentScore": 0.318281316666667, "enrollmentScorePlus": 48.70621805326589, "wealthScore": 115.77, "colors": {"absolute": null, "absolutePlus": null, "esAbsolute": "#3b82f6", "esPlusAbsolute": "#3b82f6", "wsAbsolute": "#3b82f6", "esRelative": "#3b82f6", "esPlusRelative": "#3b82f6", "wsRelative": "#3b82f6", "comboRelative": "#3b82f6", "comboPlusRelative": "#3b82f6", "es": "#3b82f6", "esPlus": "#3b82f6", "ws": "#3b82f6", "combo": "#3b82f6", "comboPlus": "#3b82f6", "esFiltered": null, "wsFiltered": null, "comboFiltered": null, "esPlusFiltered": null, "wsPlusFiltered": null, "comboPlusFiltered": null, "esRelativeFiltered": null, "wsRelativeFiltered": null, "comboRelativeFiltered": null, "esPlusRelativeFiltered": null, "comboPlusRelativeFiltered": null}}, {"geoid": "300310005021", "enrollmentScore": 11.9587568133761, "enrollmentScorePlus": 394.9539962476273, "wealthScore": 679.05, "colors": {"absolute": null, "absolutePlus": null, "esAbsolute": "#3b82f6", "esPlusAbsolute": "#3b82f6", "wsAbsolute": "#3b82f6", "esRelative": "#ef4444", "esPlusRelative": "#ef4444", "wsRelative": "#ef4444", "comboRelative": "#ef4444", "comboPlusRelative": "#ef4444", "es": "#eab308", "esPlus": "#eab308", "ws": "#f97316", "combo": "#eab308", "comboPlus": "#eab308", "esFiltered": null, "wsFiltered": null, "comboFiltered": null, "esPlusFiltered": null, "wsPlusFiltered": null, "comboPlusFiltered": null, "esRelativeFiltered": null, "wsRelativeFiltered": null, "comboRelativeFiltered": null, "esPlusRelativeFiltered": null, "comboPlusRelativeFiltered": null}}, {"geoid": "300310005022", "enrollmentScore": 9.41203796982632, "enrollmentScorePlus": 337.952976541398, "wealthScore": 497.68, "colors": {"absolute": null, "absolutePlus": null, "esAbsolute": "#3b82f6", "esPlusAbsolute": "#3b82f6", "wsAbsolute": "#3b82f6", "esRelative": "#ef4444", "esPlusRelative": "#ef4444", "wsRelative": "#f97316", "comboRelative": "#f97316", "comboPlusRelative": "#f97316", "es": "#eab308", "esPlus": "#eab308", "ws": "#eab308", "combo": "#eab308", "comboPlus": "#eab308", "esFiltered": null, "wsFiltered": null, "comboFiltered": null, "esPlusFiltered": null, "wsPlusFiltered": null, "comboPlusFiltered": null, "esRelativeFiltered": null, "wsRelativeFiltered": null, "comboRelativeFiltered": null, "esPlusRelativeFiltered": null, "comboPlusRelativeFiltered": null}}, {"geoid": "300310005023", "enrollmentScore": 12.3293203619313, "enrollmentScorePlus": 395.24124878878683, "wealthScore": 577.96, "colors": {"absolute": null, "absolutePlus": null, "esAbsolute": "#3b82f6", "esPlusAbsolute": "#3b82f6", "wsAbsolute": "#3b82f6", "esRelative": "#ef4444", "esPlusRelative": "#ef4444", "wsRelative": "#f97316", "comboRelative": "#f97316", "comboPlusRelative": "#f97316", "es": "#f97316", "esPlus": "#eab308", "ws": "#eab308", "combo": "#eab308", "comboPlus": "#eab308", "esFiltered": null, "wsFiltered": null, "comboFiltered": null, "esPlusFiltered": null, "wsPlusFiltered": null, "comboPlusFiltered": null, "esRelativeFiltered": null, "wsRelativeFiltered": null, "comboRelativeFiltered": null, "esPlusRelativeFiltered": null, "comboPlusRelativeFiltered": null}}, {"geoid": "300310005024", "enrollmentScore": 10.6992160177138, "enrollmentScorePlus": 307.06050284564196, "wealthScore": 358.2, "colors": {"absolute": null, "absolutePlus": null, "esAbsolute": "#3b82f6", "esPlusAbsolute": "#3b82f6", "wsAbsolute": "#3b82f6", "esRelative": "#ef4444", "esPlusRelative": "#f97316", "wsRelative": "#eab308", "comboRelative": "#eab308", "comboPlusRelative": "#eab308", "es": "#eab308", "esPlus": "#eab308", "ws": "#3b82f6", "combo": "#3b82f6", "comboPlus": "#3b82f6", "esFiltered": null, "wsFiltered": null, "comboFiltered": null, "esPlusFiltered": null, "wsPlusFiltered": null, "comboPlusFiltered": null, "esRelativeFiltered": null, "wsRelativeFiltered": null, "comboRelativeFiltered": null, "esPlusRelativeFiltered": null, "comboPlusRelativeFiltered": null}}, {"geoid": "300310005041", "enrollmentScore": 1.37252775, "enrollmentScorePlus": 91.21249360992515, "wealthScore": 66.82, "colors": {"absolute": null, "absolutePlus": null, "esAbsolute": "#3b82f6", "esPlusAbsolute": "#3b82f6", "wsAbsolute": "#3b82f6", "esRelative": "#3b82f6", "esPlusRelative": "#3b82f6", "wsRelative": "#3b82f6", "comboRelative": "#3b82f6", "comboPlusRelative": "#3b82f6", "es": "#3b82f6", "esPlus": "#3b82f6", "ws": "#3b82f6", "combo": "#3b82f6", "comboPlus": "#3b82f6", "esFiltered": null, "wsFiltered": null, "comboFiltered": null, "esPlusFiltered": null, "wsPlusFiltered": null, "comboPlusFiltered": null, "esRelativeFiltered": null, "wsRelativeFiltered": null, "comboRelativeFiltered": null, "esPlusRelativeFiltered": null, "comboPlusRelativeFiltered": null}}, {"geoid": "300310005042", "enrollmentScore": 0, "enrollmentScorePlus": 0, "wealthScore": 60.54, "colors": {"absolute": null, "absolutePlus": null, "esAbsolute": null, "esPlusAbsolute": null, "wsAbsolute": "#3b82f6", "esRelative": null, "esPlusRelative": null, "wsRelative": "#3b82f6", "comboRelative": null, "comboPlusRelative": null, "es": null, "esPlus": null, "ws": "#3b82f6", "combo": null, "comboPlus": null, "esFiltered": null, "wsFiltered": null, "comboFiltered": null, "esPlusFiltered": null, "wsPlusFiltered": null, "comboPlusFiltered": null, "esRelativeFiltered": null, "wsRelativeFiltered": null, "comboRelativeFiltered": null, "esPlusRelativeFiltered": null, "comboPlusRelativeFiltered": null}}, {"geoid": "300310005051", "enrollmentScore": 11.9587568133761, "enrollmentScorePlus": 415.6663985860263, "wealthScore": 720.58, "colors": {"absolute": null, "absolutePlus": null, "esAbsolute": "#3b82f6", "esPlusAbsolute": "#3b82f6", "wsAbsolute": "#3b82f6", "esRelative": "#ef4444", "esPlusRelative": "#ef4444", "wsRelative": "#ef4444", "comboRelative": "#ef4444", "comboPlusRelative": "#ef4444", "es": "#eab308", "esPlus": "#f97316", "ws": "#f97316", "combo": "#eab308", "comboPlus": "#f97316", "esFiltered": null, "wsFiltered": null, "comboFiltered": null, "esPlusFiltered": null, "wsPlusFiltered": null, "comboPlusFiltered": null, "esRelativeFiltered": null, "wsRelativeFiltered": null, "comboRelativeFiltered": null, "esPlusRelativeFiltered": null, "comboPlusRelativeFiltered": null}}, {"geoid": "300310005052", "enrollmentScore": 12.3109366666667, "enrollmentScorePlus": 439.9260929760714, "wealthScore": 727.2, "colors": {"absolute": null, "absolutePlus": null, "esAbsolute": "#3b82f6", "esPlusAbsolute": "#3b82f6", "wsAbsolute": "#3b82f6", "esRelative": "#ef4444", "esPlusRelative": "#ef4444", "wsRelative": "#ef4444", "comboRelative": "#ef4444", "comboPlusRelative": "#ef4444", "es": "#f97316", "esPlus": "#ef4444", "ws": "#f97316", "combo": "#f97316", "comboPlus": "#f97316", "esFiltered": null, "wsFiltered": null, "comboFiltered": null, "esPlusFiltered": null, "wsPlusFiltered": null, "comboPlusFiltered": null, "esRelativeFiltered": null, "wsRelativeFiltered": null, "comboRelativeFiltered": null, "esPlusRelativeFiltered": null, "comboPlusRelativeFiltered": null}}, {"geoid": "300310005053", "enrollmentScore": 10.9959454450152, "enrollmentScorePlus": 395.14891422077017, "wealthScore": 725.47, "colors": {"absolute": null, "absolutePlus": null, "esAbsolute": "#3b82f6", "esPlusAbsolute": "#3b82f6", "wsAbsolute": "#3b82f6", "esRelative": "#ef4444", "esPlusRelative": "#ef4444", "wsRelative": "#ef4444", "comboRelative": "#ef4444", "comboPlusRelative": "#ef4444", "es": "#eab308", "esPlus": "#eab308", "ws": "#f97316", "combo": "#eab308", "comboPlus": "#eab308", "esFiltered": null, "wsFiltered": null, "comboFiltered": null, "esPlusFiltered": null, "wsPlusFiltered": null, "comboPlusFiltered": null, "esRelativeFiltered": null, "wsRelativeFiltered": null, "comboRelativeFiltered": null, "esPlusRelativeFiltered": null, "comboPlusRelativeFiltered": null}}, {"geoid": "300310005061", "enrollmentScore": 12.3774196489406, "enrollmentScorePlus": 436.221460479401, "wealthScore": 849.29, "colors": {"absolute": null, "absolutePlus": null, "esAbsolute": "#3b82f6", "esPlusAbsolute": "#3b82f6", "wsAbsolute": "#3b82f6", "esRelative": "#ef4444", "esPlusRelative": "#ef4444", "wsRelative": "#ef4444", "comboRelative": "#ef4444", "comboPlusRelative": "#ef4444", "es": "#ef4444", "esPlus": "#ef4444", "ws": "#ef4444", "combo": "#ef4444", "comboPlus": "#ef4444", "esFiltered": null, "wsFiltered": null, "comboFiltered": null, "esPlusFiltered": null, "wsPlusFiltered": null, "comboPlusFiltered": null, "esRelativeFiltered": null, "wsRelativeFiltered": null, "comboRelativeFiltered": null, "esPlusRelativeFiltered": null, "comboPlusRelativeFiltered": null}}, {"geoid": "300310005062", "enrollmentScore": 12.0355617504344, "enrollmentScorePlus": 421.41662251712916, "wealthScore": 835.29, "colors": {"absolute": null, "absolutePlus": null, "esAbsolute": "#3b82f6", "esPlusAbsolute": "#3b82f6", "wsAbsolute": "#3b82f6", "esRelative": "#ef4444", "esPlusRelative": "#ef4444", "wsRelative": "#ef4444", "comboRelative": "#ef4444", "comboPlusRelative": "#ef4444", "es": "#f97316", "esPlus": "#f97316", "ws": "#ef4444", "combo": "#f97316", "comboPlus": "#f97316", "esFiltered": null, "wsFiltered": null, "comboFiltered": null, "esPlusFiltered": null, "wsPlusFiltered": null, "comboPlusFiltered": null, "esRelativeFiltered": null, "wsRelativeFiltered": null, "comboRelativeFiltered": null, "esPlusRelativeFiltered": null, "comboPlusRelativeFiltered": null}}, {"geoid": "300310005063", "enrollmentScore": 11.7089661619128, "enrollmentScorePlus": 411.2683636480308, "wealthScore": 833.55, "colors": {"absolute": null, "absolutePlus": null, "esAbsolute": "#3b82f6", "esPlusAbsolute": "#3b82f6", "wsAbsolute": "#3b82f6", "esRelative": "#ef4444", "esPlusRelative": "#ef4444", "wsRelative": "#ef4444", "comboRelative": "#ef4444", "comboPlusRelative": "#ef4444", "es": "#eab308", "esPlus": "#f97316", "ws": "#ef4444", "combo": "#eab308", "comboPlus": "#f97316", "esFiltered": null, "wsFiltered": null, "comboFiltered": null, "esPlusFiltered": null, "wsPlusFiltered": null, "comboPlusFiltered": null, "esRelativeFiltered": null, "wsRelativeFiltered": null, "comboRelativeFiltered": null, "esPlusRelativeFiltered": null, "comboPlusRelativeFiltered": null}}, {"geoid": "300310005071", "enrollmentScore": 9.52840768179308, "enrollmentScorePlus": 326.98362645092857, "wealthScore": 541.29, "colors": {"absolute": null, "absolutePlus": null, "esAbsolute": "#3b82f6", "esPlusAbsolute": "#3b82f6", "wsAbsolute": "#3b82f6", "esRelative": "#ef4444", "esPlusRelative": "#f97316", "wsRelative": "#f97316", "comboRelative": "#f97316", "comboPlusRelative": "#f97316", "es": "#eab308", "esPlus": "#eab308", "ws": "#eab308", "combo": "#eab308", "comboPlus": "#eab308", "esFiltered": null, "wsFiltered": null, "comboFiltered": null, "esPlusFiltered": null, "wsPlusFiltered": null, "comboPlusFiltered": null, "esRelativeFiltered": null, "wsRelativeFiltered": null, "comboRelativeFiltered": null, "esPlusRelativeFiltered": null, "comboPlusRelativeFiltered": null}}, {"geoid": "300310005072", "enrollmentScore": 11.3819150299495, "enrollmentScorePlus": 412.72514865616535, "wealthScore": 834.84, "colors": {"absolute": null, "absolutePlus": null, "esAbsolute": "#3b82f6", "esPlusAbsolute": "#3b82f6", "wsAbsolute": "#3b82f6", "esRelative": "#ef4444", "esPlusRelative": "#ef4444", "wsRelative": "#ef4444", "comboRelative": "#ef4444", "comboPlusRelative": "#ef4444", "es": "#eab308", "esPlus": "#f97316", "ws": "#ef4444", "combo": "#eab308", "comboPlus": "#f97316", "esFiltered": null, "wsFiltered": null, "comboFiltered": null, "esPlusFiltered": null, "wsPlusFiltered": null, "comboPlusFiltered": null, "esRelativeFiltered": null, "wsRelativeFiltered": null, "comboRelativeFiltered": null, "esPlusRelativeFiltered": null, "comboPlusRelativeFiltered": null}}, {"geoid": "300310006001", "enrollmentScore": 11.7391782007303, "enrollmentScorePlus": 425.04161344651584, "wealthScore": 787.03, "colors": {"absolute": null, "absolutePlus": null, "esAbsolute": "#3b82f6", "esPlusAbsolute": "#3b82f6", "wsAbsolute": "#3b82f6", "esRelative": "#ef4444", "esPlusRelative": "#ef4444", "wsRelative": "#ef4444", "comboRelative": "#ef4444", "comboPlusRelative": "#ef4444", "es": "#eab308", "esPlus": "#f97316", "ws": "#ef4444", "combo": "#eab308", "comboPlus": "#f97316", "esFiltered": null, "wsFiltered": null, "comboFiltered": null, "esPlusFiltered": null, "wsPlusFiltered": null, "comboPlusFiltered": null, "esRelativeFiltered": null, "wsRelativeFiltered": null, "comboRelativeFiltered": null, "esPlusRelativeFiltered": null, "comboPlusRelativeFiltered": null}}, {"geoid": "300310006002", "enrollmentScore": 12.3917666666667, "enrollmentScorePlus": 434.24219972069506, "wealthScore": 883.64, "colors": {"absolute": null, "absolutePlus": null, "esAbsolute": "#3b82f6", "esPlusAbsolute": "#3b82f6", "wsAbsolute": "#3b82f6", "esRelative": "#ef4444", "esPlusRelative": "#ef4444", "wsRelative": "#ef4444", "comboRelative": "#ef4444", "comboPlusRelative": "#ef4444", "es": "#ef4444", "esPlus": "#ef4444", "ws": "#ef4444", "combo": "#ef4444", "comboPlus": "#ef4444", "esFiltered": null, "wsFiltered": null, "comboFiltered": null, "esPlusFiltered": null, "wsPlusFiltered": null, "comboPlusFiltered": null, "esRelativeFiltered": null, "wsRelativeFiltered": null, "comboRelativeFiltered": null, "esPlusRelativeFiltered": null, "comboPlusRelativeFiltered": null}}, {"geoid": "300310007011", "enrollmentScore": 12.0728618300428, "enrollmentScorePlus": 416.25829485066953, "wealthScore": 666.66, "colors": {"absolute": null, "absolutePlus": null, "esAbsolute": "#3b82f6", "esPlusAbsolute": "#3b82f6", "wsAbsolute": "#3b82f6", "esRelative": "#ef4444", "esPlusRelative": "#ef4444", "wsRelative": "#ef4444", "comboRelative": "#ef4444", "comboPlusRelative": "#ef4444", "es": "#f97316", "esPlus": "#f97316", "ws": "#f97316", "combo": "#f97316", "comboPlus": "#f97316", "esFiltered": null, "wsFiltered": null, "comboFiltered": null, "esPlusFiltered": null, "wsPlusFiltered": null, "comboPlusFiltered": null, "esRelativeFiltered": null, "wsRelativeFiltered": null, "comboRelativeFiltered": null, "esPlusRelativeFiltered": null, "comboPlusRelativeFiltered": null}}, {"geoid": "300310007012", "enrollmentScore": 12.362330908057, "enrollmentScorePlus": 443.7492360529566, "wealthScore": 849.29, "colors": {"absolute": null, "absolutePlus": null, "esAbsolute": "#3b82f6", "esPlusAbsolute": "#3b82f6", "wsAbsolute": "#3b82f6", "esRelative": "#ef4444", "esPlusRelative": "#ef4444", "wsRelative": "#ef4444", "comboRelative": "#ef4444", "comboPlusRelative": "#ef4444", "es": "#f97316", "esPlus": "#ef4444", "ws": "#ef4444", "combo": "#f97316", "comboPlus": "#ef4444", "esFiltered": null, "wsFiltered": null, "comboFiltered": null, "esPlusFiltered": null, "wsPlusFiltered": null, "comboPlusFiltered": null, "esRelativeFiltered": null, "wsRelativeFiltered": null, "comboRelativeFiltered": null, "esPlusRelativeFiltered": null, "comboPlusRelativeFiltered": null}}, {"geoid": "300310007013", "enrollmentScore": 12.3544665870582, "enrollmentScorePlus": 444.5167689401148, "wealthScore": 830.78, "colors": {"absolute": null, "absolutePlus": null, "esAbsolute": "#3b82f6", "esPlusAbsolute": "#3b82f6", "wsAbsolute": "#3b82f6", "esRelative": "#ef4444", "esPlusRelative": "#ef4444", "wsRelative": "#ef4444", "comboRelative": "#ef4444", "comboPlusRelative": "#ef4444", "es": "#f97316", "esPlus": "#ef4444", "ws": "#ef4444", "combo": "#f97316", "comboPlus": "#ef4444", "esFiltered": null, "wsFiltered": null, "comboFiltered": null, "esPlusFiltered": null, "wsPlusFiltered": null, "comboPlusFiltered": null, "esRelativeFiltered": null, "wsRelativeFiltered": null, "comboRelativeFiltered": null, "esPlusRelativeFiltered": null, "comboPlusRelativeFiltered": null}}, {"geoid": "300310007014", "enrollmentScore": 12.3774196489406, "enrollmentScorePlus": 439.8541080935094, "wealthScore": 808.53, "colors": {"absolute": null, "absolutePlus": null, "esAbsolute": "#3b82f6", "esPlusAbsolute": "#3b82f6", "wsAbsolute": "#3b82f6", "esRelative": "#ef4444", "esPlusRelative": "#ef4444", "wsRelative": "#ef4444", "comboRelative": "#ef4444", "comboPlusRelative": "#ef4444", "es": "#ef4444", "esPlus": "#ef4444", "ws": "#ef4444", "combo": "#ef4444", "comboPlus": "#ef4444", "esFiltered": null, "wsFiltered": null, "comboFiltered": null, "esPlusFiltered": null, "wsPlusFiltered": null, "comboPlusFiltered": null, "esRelativeFiltered": null, "wsRelativeFiltered": null, "comboRelativeFiltered": null, "esPlusRelativeFiltered": null, "comboPlusRelativeFiltered": null}}, {"geoid": "300310007031", "enrollmentScore": 12.3109366666667, "enrollmentScorePlus": 426.13934525854796, "wealthScore": 697.69, "colors": {"absolute": null, "absolutePlus": null, "esAbsolute": "#3b82f6", "esPlusAbsolute": "#3b82f6", "wsAbsolute": "#3b82f6", "esRelative": "#ef4444", "esPlusRelative": "#ef4444", "wsRelative": "#ef4444", "comboRelative": "#ef4444", "comboPlusRelative": "#ef4444", "es": "#f97316", "esPlus": "#f97316", "ws": "#f97316", "combo": "#f97316", "comboPlus": "#f97316", "esFiltered": null, "wsFiltered": null, "comboFiltered": null, "esPlusFiltered": null, "wsPlusFiltered": null, "comboPlusFiltered": null, "esRelativeFiltered": null, "wsRelativeFiltered": null, "comboRelativeFiltered": null, "esPlusRelativeFiltered": null, "comboPlusRelativeFiltered": null}}, {"geoid": "300310007032", "enrollmentScore": 12.3293203619313, "enrollmentScorePlus": 428.8092335258555, "wealthScore": 701.47, "colors": {"absolute": null, "absolutePlus": null, "esAbsolute": "#3b82f6", "esPlusAbsolute": "#3b82f6", "wsAbsolute": "#3b82f6", "esRelative": "#ef4444", "esPlusRelative": "#ef4444", "wsRelative": "#ef4444", "comboRelative": "#ef4444", "comboPlusRelative": "#ef4444", "es": "#f97316", "esPlus": "#f97316", "ws": "#f97316", "combo": "#f97316", "comboPlus": "#f97316", "esFiltered": null, "wsFiltered": null, "comboFiltered": null, "esPlusFiltered": null, "wsPlusFiltered": null, "comboPlusFiltered": null, "esRelativeFiltered": null, "wsRelativeFiltered": null, "comboRelativeFiltered": null, "esPlusRelativeFiltered": null, "comboPlusRelativeFiltered": null}}, {"geoid": "300310007041", "enrollmentScore": 12.3109366666667, "enrollmentScorePlus": 423.7973774362488, "wealthScore": 701.47, "colors": {"absolute": null, "absolutePlus": null, "esAbsolute": "#3b82f6", "esPlusAbsolute": "#3b82f6", "wsAbsolute": "#3b82f6", "esRelative": "#ef4444", "esPlusRelative": "#ef4444", "wsRelative": "#ef4444", "comboRelative": "#ef4444", "comboPlusRelative": "#ef4444", "es": "#f97316", "esPlus": "#f97316", "ws": "#f97316", "combo": "#f97316", "comboPlus": "#f97316", "esFiltered": null, "wsFiltered": null, "comboFiltered": null, "esPlusFiltered": null, "wsPlusFiltered": null, "comboPlusFiltered": null, "esRelativeFiltered": null, "wsRelativeFiltered": null, "comboRelativeFiltered": null, "esPlusRelativeFiltered": null, "comboPlusRelativeFiltered": null}}, {"geoid": "300310007042", "enrollmentScore": 12.3463611819187, "enrollmentScorePlus": 448.2772901616131, "wealthScore": 740.41, "colors": {"absolute": null, "absolutePlus": null, "esAbsolute": "#3b82f6", "esPlusAbsolute": "#3b82f6", "wsAbsolute": "#3b82f6", "esRelative": "#ef4444", "esPlusRelative": "#ef4444", "wsRelative": "#ef4444", "comboRelative": "#ef4444", "comboPlusRelative": "#ef4444", "es": "#f97316", "esPlus": "#ef4444", "ws": "#f97316", "combo": "#f97316", "comboPlus": "#f97316", "esFiltered": null, "wsFiltered": null, "comboFiltered": null, "esPlusFiltered": null, "wsPlusFiltered": null, "comboPlusFiltered": null, "esRelativeFiltered": null, "wsRelativeFiltered": null, "comboRelativeFiltered": null, "esPlusRelativeFiltered": null, "comboPlusRelativeFiltered": null}}, {"geoid": "300310007043", "enrollmentScore": 12.3293203619313, "enrollmentScorePlus": 432.5569766160029, "wealthScore": 723.93, "colors": {"absolute": null, "absolutePlus": null, "esAbsolute": "#3b82f6", "esPlusAbsolute": "#3b82f6", "wsAbsolute": "#3b82f6", "esRelative": "#ef4444", "esPlusRelative": "#ef4444", "wsRelative": "#ef4444", "comboRelative": "#ef4444", "comboPlusRelative": "#ef4444", "es": "#f97316", "esPlus": "#ef4444", "ws": "#f97316", "combo": "#f97316", "comboPlus": "#f97316", "esFiltered": null, "wsFiltered": null, "comboFiltered": null, "esPlusFiltered": null, "wsPlusFiltered": null, "comboPlusFiltered": null, "esRelativeFiltered": null, "wsRelativeFiltered": null, "comboRelativeFiltered": null, "esPlusRelativeFiltered": null, "comboPlusRelativeFiltered": null}}, {"geoid": "300310008001", "enrollmentScore": 12.3917666666667, "enrollmentScorePlus": 431.912899274666, "wealthScore": 757.09, "colors": {"absolute": null, "absolutePlus": null, "esAbsolute": "#3b82f6", "esPlusAbsolute": "#3b82f6", "wsAbsolute": "#3b82f6", "esRelative": "#ef4444", "esPlusRelative": "#ef4444", "wsRelative": "#ef4444", "comboRelative": "#ef4444", "comboPlusRelative": "#ef4444", "es": "#ef4444", "esPlus": "#f97316", "ws": "#ef4444", "combo": "#ef4444", "comboPlus": "#f97316", "esFiltered": null, "wsFiltered": null, "comboFiltered": null, "esPlusFiltered": null, "wsPlusFiltered": null, "comboPlusFiltered": null, "esRelativeFiltered": null, "wsRelativeFiltered": null, "comboRelativeFiltered": null, "esPlusRelativeFiltered": null, "comboPlusRelativeFiltered": null}}, {"geoid": "300310008002", "enrollmentScore": 12.3699757530836, "enrollmentScorePlus": 446.68738070803516, "wealthScore": 779.24, "colors": {"absolute": null, "absolutePlus": null, "esAbsolute": "#3b82f6", "esPlusAbsolute": "#3b82f6", "wsAbsolute": "#3b82f6", "esRelative": "#ef4444", "esPlusRelative": "#ef4444", "wsRelative": "#ef4444", "comboRelative": "#ef4444", "comboPlusRelative": "#ef4444", "es": "#ef4444", "esPlus": "#ef4444", "ws": "#ef4444", "combo": "#ef4444", "comboPlus": "#ef4444", "esFiltered": null, "wsFiltered": null, "comboFiltered": null, "esPlusFiltered": null, "wsPlusFiltered": null, "comboPlusFiltered": null, "esRelativeFiltered": null, "wsRelativeFiltered": null, "comboRelativeFiltered": null, "esPlusRelativeFiltered": null, "comboPlusRelativeFiltered": null}}, {"geoid": "300310008003", "enrollmentScore": 12.362330908057, "enrollmentScorePlus": 442.61470708561984, "wealthScore": 796.91, "colors": {"absolute": null, "absolutePlus": null, "esAbsolute": "#3b82f6", "esPlusAbsolute": "#3b82f6", "wsAbsolute": "#3b82f6", "esRelative": "#ef4444", "esPlusRelative": "#ef4444", "wsRelative": "#ef4444", "comboRelative": "#ef4444", "comboPlusRelative": "#ef4444", "es": "#f97316", "esPlus": "#ef4444", "ws": "#ef4444", "combo": "#f97316", "comboPlus": "#ef4444", "esFiltered": null, "wsFiltered": null, "comboFiltered": null, "esPlusFiltered": null, "wsPlusFiltered": null, "comboPlusFiltered": null, "esRelativeFiltered": null, "wsRelativeFiltered": null, "comboRelativeFiltered": null, "esPlusRelativeFiltered": null, "comboPlusRelativeFiltered": null}}, {"geoid": "300310009001", "enrollmentScore": 12.362330908057, "enrollmentScorePlus": 447.7855533273403, "wealthScore": 799.76, "colors": {"absolute": null, "absolutePlus": null, "esAbsolute": "#3b82f6", "esPlusAbsolute": "#3b82f6", "wsAbsolute": "#3b82f6", "esRelative": "#ef4444", "esPlusRelative": "#ef4444", "wsRelative": "#ef4444", "comboRelative": "#ef4444", "comboPlusRelative": "#ef4444", "es": "#f97316", "esPlus": "#ef4444", "ws": "#ef4444", "combo": "#f97316", "comboPlus": "#ef4444", "esFiltered": null, "wsFiltered": null, "comboFiltered": null, "esPlusFiltered": null, "wsPlusFiltered": null, "comboPlusFiltered": null, "esRelativeFiltered": null, "wsRelativeFiltered": null, "comboRelativeFiltered": null, "esPlusRelativeFiltered": null, "comboPlusRelativeFiltered": null}}, {"geoid": "300310009002", "enrollmentScore": 12.3463611819187, "enrollmentScorePlus": 443.076540485318, "wealthScore": 719.6, "colors": {"absolute": null, "absolutePlus": null, "esAbsolute": "#3b82f6", "esPlusAbsolute": "#3b82f6", "wsAbsolute": "#3b82f6", "esRelative": "#ef4444", "esPlusRelative": "#ef4444", "wsRelative": "#ef4444", "comboRelative": "#ef4444", "comboPlusRelative": "#ef4444", "es": "#f97316", "esPlus": "#ef4444", "ws": "#f97316", "combo": "#f97316", "comboPlus": "#f97316", "esFiltered": null, "wsFiltered": null, "comboFiltered": null, "esPlusFiltered": null, "wsPlusFiltered": null, "comboPlusFiltered": null, "esRelativeFiltered": null, "wsRelativeFiltered": null, "comboRelativeFiltered": null, "esPlusRelativeFiltered": null, "comboPlusRelativeFiltered": null}}, {"geoid": "300310009003", "enrollmentScore": 12.3379892286334, "enrollmentScorePlus": 444.70937503034844, "wealthScore": 748.88, "colors": {"absolute": null, "absolutePlus": null, "esAbsolute": "#3b82f6", "esPlusAbsolute": "#3b82f6", "wsAbsolute": "#3b82f6", "esRelative": "#ef4444", "esPlusRelative": "#ef4444", "wsRelative": "#ef4444", "comboRelative": "#ef4444", "comboPlusRelative": "#ef4444", "es": "#f97316", "esPlus": "#ef4444", "ws": "#f97316", "combo": "#f97316", "comboPlus": "#f97316", "esFiltered": null, "wsFiltered": null, "comboFiltered": null, "esPlusFiltered": null, "wsPlusFiltered": null, "comboPlusFiltered": null, "esRelativeFiltered": null, "wsRelativeFiltered": null, "comboRelativeFiltered": null, "esPlusRelativeFiltered": null, "comboPlusRelativeFiltered": null}}, {"geoid": "300310010011", "enrollmentScore": 12.3774196489406, "enrollmentScorePlus": 423.66918426069407, "wealthScore": 633.87, "colors": {"absolute": null, "absolutePlus": null, "esAbsolute": "#3b82f6", "esPlusAbsolute": "#3b82f6", "wsAbsolute": "#3b82f6", "esRelative": "#ef4444", "esPlusRelative": "#ef4444", "wsRelative": "#f97316", "comboRelative": "#f97316", "comboPlusRelative": "#f97316", "es": "#ef4444", "esPlus": "#f97316", "ws": "#eab308", "combo": "#eab308", "comboPlus": "#eab308", "esFiltered": null, "wsFiltered": null, "comboFiltered": null, "esPlusFiltered": null, "wsPlusFiltered": null, "comboPlusFiltered": null, "esRelativeFiltered": null, "wsRelativeFiltered": null, "comboRelativeFiltered": null, "esPlusRelativeFiltered": null, "comboPlusRelativeFiltered": null}}, {"geoid": "300310010012", "enrollmentScore": 12.3544665870582, "enrollmentScorePlus": 403.01489388311126, "wealthScore": 536.6, "colors": {"absolute": null, "absolutePlus": null, "esAbsolute": "#3b82f6", "esPlusAbsolute": "#3b82f6", "wsAbsolute": "#3b82f6", "esRelative": "#ef4444", "esPlusRelative": "#ef4444", "wsRelative": "#f97316", "comboRelative": "#f97316", "comboPlusRelative": "#f97316", "es": "#f97316", "esPlus": "#f97316", "ws": "#eab308", "combo": "#eab308", "comboPlus": "#eab308", "esFiltered": null, "wsFiltered": null, "comboFiltered": null, "esPlusFiltered": null, "wsPlusFiltered": null, "comboPlusFiltered": null, "esRelativeFiltered": null, "wsRelativeFiltered": null, "comboRelativeFiltered": null, "esPlusRelativeFiltered": null, "comboPlusRelativeFiltered": null}}, {"geoid": "300310010021", "enrollmentScore": 12.3774196489406, "enrollmentScorePlus": 431.28805294285746, "wealthScore": 698.23, "colors": {"absolute": null, "absolutePlus": null, "esAbsolute": "#3b82f6", "esPlusAbsolute": "#3b82f6", "wsAbsolute": "#3b82f6", "esRelative": "#ef4444", "esPlusRelative": "#ef4444", "wsRelative": "#ef4444", "comboRelative": "#ef4444", "comboPlusRelative": "#ef4444", "es": "#ef4444", "esPlus": "#f97316", "ws": "#f97316", "combo": "#f97316", "comboPlus": "#f97316", "esFiltered": null, "wsFiltered": null, "comboFiltered": null, "esPlusFiltered": null, "wsPlusFiltered": null, "comboPlusFiltered": null, "esRelativeFiltered": null, "wsRelativeFiltered": null, "comboRelativeFiltered": null, "esPlusRelativeFiltered": null, "comboPlusRelativeFiltered": null}}, {"geoid": "300310010022", "enrollmentScore": 12.3917666666667, "enrollmentScorePlus": 430.365854829297, "wealthScore": 822.95, "colors": {"absolute": null, "absolutePlus": null, "esAbsolute": "#3b82f6", "esPlusAbsolute": "#3b82f6", "wsAbsolute": "#3b82f6", "esRelative": "#ef4444", "esPlusRelative": "#ef4444", "wsRelative": "#ef4444", "comboRelative": "#ef4444", "comboPlusRelative": "#ef4444", "es": "#ef4444", "esPlus": "#f97316", "ws": "#ef4444", "combo": "#ef4444", "comboPlus": "#f97316", "esFiltered": null, "wsFiltered": null, "comboFiltered": null, "esPlusFiltered": null, "wsPlusFiltered": null, "comboPlusFiltered": null, "esRelativeFiltered": null, "wsRelativeFiltered": null, "comboRelativeFiltered": null, "esPlusRelativeFiltered": null, "comboPlusRelativeFiltered": null}}, {"geoid": "300310010023", "enrollmentScore": 12.3917666666667, "enrollmentScorePlus": 400.91156828922783, "wealthScore": 762.76, "colors": {"absolute": null, "absolutePlus": null, "esAbsolute": "#3b82f6", "esPlusAbsolute": "#3b82f6", "wsAbsolute": "#3b82f6", "esRelative": "#ef4444", "esPlusRelative": "#ef4444", "wsRelative": "#ef4444", "comboRelative": "#ef4444", "comboPlusRelative": "#ef4444", "es": "#ef4444", "esPlus": "#f97316", "ws": "#ef4444", "combo": "#ef4444", "comboPlus": "#f97316", "esFiltered": null, "wsFiltered": null, "comboFiltered": null, "esPlusFiltered": null, "wsPlusFiltered": null, "comboPlusFiltered": null, "esRelativeFiltered": null, "wsRelativeFiltered": null, "comboRelativeFiltered": null, "esPlusRelativeFiltered": null, "comboPlusRelativeFiltered": null}}, {"geoid": "300310010024", "enrollmentScore": 12.3917666666667, "enrollmentScorePlus": 427.95671650117515, "wealthScore": 643.03, "colors": {"absolute": null, "absolutePlus": null, "esAbsolute": "#3b82f6", "esPlusAbsolute": "#3b82f6", "wsAbsolute": "#3b82f6", "esRelative": "#ef4444", "esPlusRelative": "#ef4444", "wsRelative": "#f97316", "comboRelative": "#f97316", "comboPlusRelative": "#f97316", "es": "#ef4444", "esPlus": "#f97316", "ws": "#eab308", "combo": "#eab308", "comboPlus": "#eab308", "esFiltered": null, "wsFiltered": null, "comboFiltered": null, "esPlusFiltered": null, "wsPlusFiltered": null, "comboPlusFiltered": null, "esRelativeFiltered": null, "wsRelativeFiltered": null, "comboRelativeFiltered": null, "esPlusRelativeFiltered": null, "comboPlusRelativeFiltered": null}}, {"geoid": "300310011011", "enrollmentScore": 12.3544665870582, "enrollmentScorePlus": 439.92171749914695, "wealthScore": 750.42, "colors": {"absolute": null, "absolutePlus": null, "esAbsolute": "#3b82f6", "esPlusAbsolute": "#3b82f6", "wsAbsolute": "#3b82f6", "esRelative": "#ef4444", "esPlusRelative": "#ef4444", "wsRelative": "#ef4444", "comboRelative": "#ef4444", "comboPlusRelative": "#ef4444", "es": "#f97316", "esPlus": "#ef4444", "ws": "#f97316", "combo": "#f97316", "comboPlus": "#f97316", "esFiltered": null, "wsFiltered": null, "comboFiltered": null, "esPlusFiltered": null, "wsPlusFiltered": null, "comboPlusFiltered": null, "esRelativeFiltered": null, "wsRelativeFiltered": null, "comboRelativeFiltered": null, "esPlusRelativeFiltered": null, "comboPlusRelativeFiltered": null}}, {"geoid": "300310011012", "enrollmentScore": 12.3774196489406, "enrollmentScorePlus": 436.0856881437384, "wealthScore": 679.05, "colors": {"absolute": null, "absolutePlus": null, "esAbsolute": "#3b82f6", "esPlusAbsolute": "#3b82f6", "wsAbsolute": "#3b82f6", "esRelative": "#ef4444", "esPlusRelative": "#ef4444", "wsRelative": "#ef4444", "comboRelative": "#ef4444", "comboPlusRelative": "#ef4444", "es": "#ef4444", "esPlus": "#ef4444", "ws": "#f97316", "combo": "#f97316", "comboPlus": "#f97316", "esFiltered": null, "wsFiltered": null, "comboFiltered": null, "esPlusFiltered": null, "wsPlusFiltered": null, "comboPlusFiltered": null, "esRelativeFiltered": null, "wsRelativeFiltered": null, "comboRelativeFiltered": null, "esPlusRelativeFiltered": null, "comboPlusRelativeFiltered": null}}, {"geoid": "300310011013", "enrollmentScore": 12.3699757530836, "enrollmentScorePlus": 434.6865592114947, "wealthScore": 679.27, "colors": {"absolute": null, "absolutePlus": null, "esAbsolute": "#3b82f6", "esPlusAbsolute": "#3b82f6", "wsAbsolute": "#3b82f6", "esRelative": "#ef4444", "esPlusRelative": "#ef4444", "wsRelative": "#ef4444", "comboRelative": "#ef4444", "comboPlusRelative": "#ef4444", "es": "#ef4444", "esPlus": "#ef4444", "ws": "#f97316", "combo": "#f97316", "comboPlus": "#f97316", "esFiltered": null, "wsFiltered": null, "comboFiltered": null, "esPlusFiltered": null, "wsPlusFiltered": null, "comboPlusFiltered": null, "esRelativeFiltered": null, "wsRelativeFiltered": null, "comboRelativeFiltered": null, "esPlusRelativeFiltered": null, "comboPlusRelativeFiltered": null}}, {"geoid": "300310011021", "enrollmentScore": 12.3463611819187, "enrollmentScorePlus": 432.3471341993719, "wealthScore": 708.34, "colors": {"absolute": null, "absolutePlus": null, "esAbsolute": "#3b82f6", "esPlusAbsolute": "#3b82f6", "wsAbsolute": "#3b82f6", "esRelative": "#ef4444", "esPlusRelative": "#ef4444", "wsRelative": "#ef4444", "comboRelative": "#ef4444", "comboPlusRelative": "#ef4444", "es": "#f97316", "esPlus": "#f97316", "ws": "#f97316", "combo": "#f97316", "comboPlus": "#f97316", "esFiltered": null, "wsFiltered": null, "comboFiltered": null, "esPlusFiltered": null, "wsPlusFiltered": null, "comboPlusFiltered": null, "esRelativeFiltered": null, "wsRelativeFiltered": null, "comboRelativeFiltered": null, "esPlusRelativeFiltered": null, "comboPlusRelativeFiltered": null}}, {"geoid": "300310011022", "enrollmentScore": 12.3699757530836, "enrollmentScorePlus": 439.1017780125663, "wealthScore": 762.56, "colors": {"absolute": null, "absolutePlus": null, "esAbsolute": "#3b82f6", "esPlusAbsolute": "#3b82f6", "wsAbsolute": "#3b82f6", "esRelative": "#ef4444", "esPlusRelative": "#ef4444", "wsRelative": "#ef4444", "comboRelative": "#ef4444", "comboPlusRelative": "#ef4444", "es": "#ef4444", "esPlus": "#ef4444", "ws": "#ef4444", "combo": "#ef4444", "comboPlus": "#ef4444", "esFiltered": null, "wsFiltered": null, "comboFiltered": null, "esPlusFiltered": null, "wsPlusFiltered": null, "comboPlusFiltered": null, "esRelativeFiltered": null, "wsRelativeFiltered": null, "comboRelativeFiltered": null, "esPlusRelativeFiltered": null, "comboPlusRelativeFiltered": null}}, {"geoid": "300310012001", "enrollmentScore": 10.8744799722392, "enrollmentScorePlus": 351.6515368852772, "wealthScore": 515.68, "colors": {"absolute": null, "absolutePlus": null, "esAbsolute": "#3b82f6", "esPlusAbsolute": "#3b82f6", "wsAbsolute": "#3b82f6", "esRelative": "#ef4444", "esPlusRelative": "#ef4444", "wsRelative": "#f97316", "comboRelative": "#f97316", "comboPlusRelative": "#f97316", "es": "#eab308", "esPlus": "#eab308", "ws": "#eab308", "combo": "#eab308", "comboPlus": "#eab308", "esFiltered": null, "wsFiltered": null, "comboFiltered": null, "esPlusFiltered": null, "wsPlusFiltered": null, "comboPlusFiltered": null, "esRelativeFiltered": null, "wsRelativeFiltered": null, "comboRelativeFiltered": null, "esPlusRelativeFiltered": null, "comboPlusRelativeFiltered": null}}, {"geoid": "300310012002", "enrollmentScore": 0, "enrollmentScorePlus": 0.3683141075866471, "wealthScore": 0, "colors": {"absolute": null, "absolutePlus": null, "esAbsolute": null, "esPlusAbsolute": "#3b82f6", "wsAbsolute": null, "esRelative": null, "esPlusRelative": "#3b82f6", "wsRelative": null, "comboRelative": null, "comboPlusRelative": null, "es": null, "esPlus": "#3b82f6", "ws": null, "combo": null, "comboPlus": null, "esFiltered": null, "wsFiltered": null, "comboFiltered": null, "esPlusFiltered": null, "wsPlusFiltered": null, "comboPlusFiltered": null, "esRelativeFiltered": null, "wsRelativeFiltered": null, "comboRelativeFiltered": null, "esPlusRelativeFiltered": null, "comboPlusRelativeFiltered": null}}, {"geoid": "300310012003", "enrollmentScore": 9.32622345315966, "enrollmentScorePlus": 335.71112816908106, "wealthScore": 445.04, "colors": {"absolute": null, "absolutePlus": null, "esAbsolute": "#3b82f6", "esPlusAbsolute": "#3b82f6", "wsAbsolute": "#3b82f6", "esRelative": "#ef4444", "esPlusRelative": "#f97316", "wsRelative": "#f97316", "comboRelative": "#f97316", "comboPlusRelative": "#f97316", "es": "#eab308", "esPlus": "#eab308", "ws": "#eab308", "combo": "#eab308", "comboPlus": "#eab308", "esFiltered": null, "wsFiltered": null, "comboFiltered": null, "esPlusFiltered": null, "wsPlusFiltered": null, "comboPlusFiltered": null, "esRelativeFiltered": null, "wsRelativeFiltered": null, "comboRelativeFiltered": null, "esPlusRelativeFiltered": null, "comboPlusRelativeFiltered": null}}, {"geoid": "300310012004", "enrollmentScore": 0, "enrollmentScorePlus": 0.27746623605402126, "wealthScore": 3.64, "colors": {"absolute": null, "absolutePlus": null, "esAbsolute": null, "esPlusAbsolute": "#3b82f6", "wsAbsolute": "#3b82f6", "esRelative": null, "esPlusRelative": "#3b82f6", "wsRelative": "#3b82f6", "comboRelative": null, "comboPlusRelative": "#3b82f6", "es": null, "esPlus": "#3b82f6", "ws": "#3b82f6", "combo": null, "comboPlus": "#3b82f6", "esFiltered": null, "wsFiltered": null, "comboFiltered": null, "esPlusFiltered": null, "wsPlusFiltered": null, "comboPlusFiltered": null, "esRelativeFiltered": null, "wsRelativeFiltered": null, "comboRelativeFiltered": null, "esPlusRelativeFiltered": null, "comboPlusRelativeFiltered": null}}, {"geoid": "300310015001", "enrollmentScore": 0, "enrollmentScorePlus": 0, "wealthScore": 0, "colors": {"absolute": null, "absolutePlus": null, "esAbsolute": null, "esPlusAbsolute": null, "wsAbsolute": null, "esRelative": null, "esPlusRelative": null, "wsRelative": null, "comboRelative": null, "comboPlusRelative": null, "es": null, "esPlus": null, "ws": null, "combo": null, "comboPlus": null, "esFiltered": null, "wsFiltered": null, "comboFiltered": null, "esPlusFiltered": null, "wsPlusFiltered": null, "comboPlusFiltered": null, "esRelativeFiltered": null, "wsRelativeFiltered": null, "comboRelativeFiltered": null, "esPlusRelativeFiltered": null, "comboPlusRelativeFiltered": null}}, {"geoid": "300310015002", "enrollmentScore": 0, "enrollmentScorePlus": 0, "wealthScore": 0, "colors": {"absolute": null, "absolutePlus": null, "esAbsolute": null, "esPlusAbsolute": null, "wsAbsolute": null, "esRelative": null, "esPlusRelative": null, "wsRelative": null, "comboRelative": null, "comboPlusRelative": null, "es": null, "esPlus": null, "ws": null, "combo": null, "comboPlus": null, "esFiltered": null, "wsFiltered": null, "comboFiltered": null, "esPlusFiltered": null, "wsPlusFiltered": null, "comboPlusFiltered": null, "esRelativeFiltered": null, "wsRelativeFiltered": null, "comboRelativeFiltered": null, "esPlusRelativeFiltered": null, "comboPlusRelativeFiltered": null}}, {"geoid": "300310015003", "enrollmentScore": 0, "enrollmentScorePlus": 0, "wealthScore": 0, "colors": {"absolute": null, "absolutePlus": null, "esAbsolute": null, "esPlusAbsolute": null, "wsAbsolute": null, "esRelative": null, "esPlusRelative": null, "wsRelative": null, "comboRelative": null, "comboPlusRelative": null, "es": null, "esPlus": null, "ws": null, "combo": null, "comboPlus": null, "esFiltered": null, "wsFiltered": null, "comboFiltered": null, "esPlusFiltered": null, "wsPlusFiltered": null, "comboPlusFiltered": null, "esRelativeFiltered": null, "wsRelativeFiltered": null, "comboRelativeFiltered": null, "esPlusRelativeFiltered": null, "comboPlusRelativeFiltered": null}}, {"geoid": "300310016001", "enrollmentScore": 0, "enrollmentScorePlus": 2.6041139601820533, "wealthScore": 4.75, "colors": {"absolute": null, "absolutePlus": null, "esAbsolute": null, "esPlusAbsolute": "#3b82f6", "wsAbsolute": "#3b82f6", "esRelative": null, "esPlusRelative": "#3b82f6", "wsRelative": "#3b82f6", "comboRelative": null, "comboPlusRelative": "#3b82f6", "es": null, "esPlus": "#3b82f6", "ws": "#3b82f6", "combo": null, "comboPlus": "#3b82f6", "esFiltered": null, "wsFiltered": null, "comboFiltered": null, "esPlusFiltered": null, "wsPlusFiltered": null, "comboPlusFiltered": null, "esRelativeFiltered": null, "wsRelativeFiltered": null, "comboRelativeFiltered": null, "esPlusRelativeFiltered": null, "comboPlusRelativeFiltered": null}}, {"geoid": "300310016002", "enrollmentScore": 0, "enrollmentScorePlus": 1.832637835500867, "wealthScore": 4.75, "colors": {"absolute": null, "absolutePlus": null, "esAbsolute": null, "esPlusAbsolute": "#3b82f6", "wsAbsolute": "#3b82f6", "esRelative": null, "esPlusRelative": "#3b82f6", "wsRelative": "#3b82f6", "comboRelative": null, "comboPlusRelative": "#3b82f6", "es": null, "esPlus": "#3b82f6", "ws": "#3b82f6", "combo": null, "comboPlus": "#3b82f6", "esFiltered": null, "wsFiltered": null, "comboFiltered": null, "esPlusFiltered": null, "wsPlusFiltered": null, "comboPlusFiltered": null, "esRelativeFiltered": null, "wsRelativeFiltered": null, "comboRelativeFiltered": null, "esPlusRelativeFiltered": null, "comboPlusRelativeFiltered": null}}, {"geoid": "300310016003", "enrollmentScore": 0, "enrollmentScorePlus": 0.5299752999294276, "wealthScore": 1.41, "colors": {"absolute": null, "absolutePlus": null, "esAbsolute": null, "esPlusAbsolute": "#3b82f6", "wsAbsolute": "#3b82f6", "esRelative": null, "esPlusRelative": "#3b82f6", "wsRelative": "#3b82f6", "comboRelative": null, "comboPlusRelative": "#3b82f6", "es": null, "esPlus": "#3b82f6", "ws": "#3b82f6", "combo": null, "comboPlus": "#3b82f6", "esFiltered": null, "wsFiltered": null, "comboFiltered": null, "esPlusFiltered": null, "wsPlusFiltered": null, "comboPlusFiltered": null, "esRelativeFiltered": null, "wsRelativeFiltered": null, "comboRelativeFiltered": null, "esPlusRelativeFiltered": null, "comboPlusRelativeFiltered": null}}, {"geoid": "300310017001", "enrollmentScore": 0, "enrollmentScorePlus": 0, "wealthScore": 0, "colors": {"absolute": null, "absolutePlus": null, "esAbsolute": null, "esPlusAbsolute": null, "wsAbsolute": null, "esRelative": null, "esPlusRelative": null, "wsRelative": null, "comboRelative": null, "comboPlusRelative": null, "es": null, "esPlus": null, "ws": null, "combo": null, "comboPlus": null, "esFiltered": null, "wsFiltered": null, "comboFiltered": null, "esPlusFiltered": null, "wsPlusFiltered": null, "comboPlusFiltered": null, "esRelativeFiltered": null, "wsRelativeFiltered": null, "comboRelativeFiltered": null, "esPlusRelativeFiltered": null, "comboPlusRelativeFiltered": null}}, {"geoid": "300310017002", "enrollmentScore": 0, "enrollmentScorePlus": 0.013632915046424901, "wealthScore": 0, "colors": {"absolute": null, "absolutePlus": null, "esAbsolute": null, "esPlusAbsolute": "#3b82f6", "wsAbsolute": null, "esRelative": null, "esPlusRelative": "#3b82f6", "wsRelative": null, "comboRelative": null, "comboPlusRelative": null, "es": null, "esPlus": "#3b82f6", "ws": null, "combo": null, "comboPlus": null, "esFiltered": null, "wsFiltered": null, "comboFiltered": null, "esPlusFiltered": null, "wsPlusFiltered": null, "comboPlusFiltered": null, "esRelativeFiltered": null, "wsRelativeFiltered": null, "comboRelativeFiltered": null, "esPlusRelativeFiltered": null, "comboPlusRelativeFiltered": null}}, {"geoid": "300310017003", "enrollmentScore": 0.177523362618599, "enrollmentScorePlus": 4.483487995592513, "wealthScore": 0, "colors": {"absolute": null, "absolutePlus": null, "esAbsolute": "#3b82f6", "esPlusAbsolute": "#3b82f6", "wsAbsolute": null, "esRelative": "#3b82f6", "esPlusRelative": "#3b82f6", "wsRelative": null, "comboRelative": null, "comboPlusRelative": null, "es": "#3b82f6", "esPlus": "#3b82f6", "ws": null, "combo": null, "comboPlus": null, "esFiltered": null, "wsFiltered": null, "comboFiltered": null, "esPlusFiltered": null, "wsPlusFiltered": null, "comboPlusFiltered": null, "esRelativeFiltered": null, "wsRelativeFiltered": null, "comboRelativeFiltered": null, "esPlusRelativeFiltered": null, "comboPlusRelativeFiltered": null}}]